nalog
